pygfe/__init__.py
pygfe/cypher.py
pygfe/pygfe.py
pygfe/util.py
pygfe/feature_client/__init__.py
pygfe/feature_client/api_client.py
pygfe/feature_client/configuration.py
pygfe/feature_client/rest.py
pygfe/feature_client/apis/__init__.py
pygfe/feature_client/apis/features_api.py
pygfe/feature_client/models/__init__.py
pygfe/feature_client/models/feature.py
pygfe/feature_client/models/feature_request.py
pygfe/feature_client/models/sequence.py
pygfe/models/__init__.py
pygfe/models/base_model_.py
pygfe/models/error.py
pygfe/models/feature.py
pygfe/models/seqdiff.py
pygfe/models/typing.py
pygfe-0.0.32.data/scripts/seq2gfe
pygfe-0.0.32.dist-info/DESCRIPTION.rst
pygfe-0.0.32.dist-info/METADATA
pygfe-0.0.32.dist-info/RECORD
pygfe-0.0.32.dist-info/WHEEL
pygfe-0.0.32.dist-info/metadata.json
pygfe-0.0.32.dist-info/top_level.txt
