Metadata-Version: 2.0
Name: pygfe
Version: 0.0.32
Summary: Python package for converting sequence annotations to gene feature enumerations (GFE).
Home-page: https://github.com/mhalagan-nmdp/pygfe
Author: Mike Halagan
Author-email: mhalagan@nmdp.org
License: LGPL 3.0
Keywords: pygfe
Platform: UNKNOWN
Classifier: Development Status :: 2 - Pre-Alpha
Classifier: Intended Audience :: Developers
Classifier: License :: OSI Approved :: GNU Lesser General Public License v3 (LGPLv3)
Classifier: Natural Language :: English
Classifier: Programming Language :: Python :: 2
Classifier: Programming Language :: Python :: 2.6
Classifier: Programming Language :: Python :: 2.7
Classifier: Programming Language :: Python :: 3
Classifier: Programming Language :: Python :: 3.3
Classifier: Programming Language :: Python :: 3.4
Classifier: Programming Language :: Python :: 3.5
Requires-Dist: atomicwrites (==1.1.5)
Requires-Dist: attrs (==18.1.0)
Requires-Dist: biopython (==1.70)
Requires-Dist: bson (==0.5.5)
Requires-Dist: certifi (==2017.11.5)
Requires-Dist: chardet (==3.0.4)
Requires-Dist: click (==6.7)
Requires-Dist: colorama (==0.3.9)
Requires-Dist: idna (==2.6)
Requires-Dist: more-itertools (==4.2.0)
Requires-Dist: neo4j-driver (==1.6.1)
Requires-Dist: neotime (==1.0.0)
Requires-Dist: numpy (==1.13.3)
Requires-Dist: pandas (==0.22.0)
Requires-Dist: pkginfo (==1.4.1)
Requires-Dist: pluggy (==0.6.0)
Requires-Dist: prompt-toolkit (==1.0.15)
Requires-Dist: py (==1.5.4)
Requires-Dist: py2neo (==4.0.0)
Requires-Dist: Pygments (==2.2.0)
Requires-Dist: PyMySQL (==0.7.11)
Requires-Dist: pytest (==3.6.3)
Requires-Dist: python-dateutil (==2.6.1)
Requires-Dist: pytz (==2017.3)
Requires-Dist: requests (==2.18.4)
Requires-Dist: requests-toolbelt (==0.8.0)
Requires-Dist: seqann
Requires-Dist: six (==1.11.0)
Requires-Dist: tqdm (==4.19.4)
Requires-Dist: twine (==1.9.1)
Requires-Dist: urllib3 (==1.22)
Requires-Dist: wcwidth (==0.1.7)
